{
    "id": 2769121483,
    "node_id": "MDIwOlJldmlld1JlcXVlc3RlZEV2ZW50Mjc2OTEyMTQ4Mw==",
    "url": "https://api.github.com/repos/ethereumclassic/ECIPs/issues/events/2769121483",
    "actor": {
      "login": "BelfordZ",
      "id": 1787231,
      "node_id": "MDQ6VXNlcjE3ODcyMzE=",
      "avatar_url": "https://avatars0.githubusercontent.com/u/1787231?v=4",
      "gravatar_id": "",
      "url": "https://api.github.com/users/BelfordZ",
      "html_url": "https://github.com/BelfordZ",
      "followers_url": "https://api.github.com/users/BelfordZ/followers",
      "following_url": "https://api.github.com/users/BelfordZ/following{/other_user}",
      "gists_url": "https://api.github.com/users/BelfordZ/gists{/gist_id}",
      "starred_url": "https://api.github.com/users/BelfordZ/starred{/owner}{/repo}",
      "subscriptions_url": "https://api.github.com/users/BelfordZ/subscriptions",
      "organizations_url": "https://api.github.com/users/BelfordZ/orgs",
      "repos_url": "https://api.github.com/users/BelfordZ/repos",
      "events_url": "https://api.github.com/users/BelfordZ/events{/privacy}",
      "received_events_url": "https://api.github.com/users/BelfordZ/received_events",
      "type": "User",
      "site_admin": false
    },
    "event": "review_requested",
    "commit_id": null,
    "commit_url": null,
    "created_at": "2019-11-04T20:30:52Z",
    "review_requester": {
      "login": "BelfordZ",
      "id": 1787231,
      "node_id": "MDQ6VXNlcjE3ODcyMzE=",
      "avatar_url": "https://avatars0.githubusercontent.com/u/1787231?v=4",
      "gravatar_id": "",
      "url": "https://api.github.com/users/BelfordZ",
      "html_url": "https://github.com/BelfordZ",
      "followers_url": "https://api.github.com/users/BelfordZ/followers",
      "following_url": "https://api.github.com/users/BelfordZ/following{/other_user}",
      "gists_url": "https://api.github.com/users/BelfordZ/gists{/gist_id}",
      "starred_url": "https://api.github.com/users/BelfordZ/starred{/owner}{/repo}",
      "subscriptions_url": "https://api.github.com/users/BelfordZ/subscriptions",
      "organizations_url": "https://api.github.com/users/BelfordZ/orgs",
      "repos_url": "https://api.github.com/users/BelfordZ/repos",
      "events_url": "https://api.github.com/users/BelfordZ/events{/privacy}",
      "received_events_url": "https://api.github.com/users/BelfordZ/received_events",
      "type": "User",
      "site_admin": false
    },
    "requested_reviewer": {
      "login": "TokenHash",
      "id": 29529586,
      "node_id": "MDQ6VXNlcjI5NTI5NTg2",
      "avatar_url": "https://avatars1.githubusercontent.com/u/29529586?v=4",
      "gravatar_id": "",
      "url": "https://api.github.com/users/TokenHash",
      "html_url": "https://github.com/TokenHash",
      "followers_url": "https://api.github.com/users/TokenHash/followers",
      "following_url": "https://api.github.com/users/TokenHash/following{/other_user}",
      "gists_url": "https://api.github.com/users/TokenHash/gists{/gist_id}",
      "starred_url": "https://api.github.com/users/TokenHash/starred{/owner}{/repo}",
      "subscriptions_url": "https://api.github.com/users/TokenHash/subscriptions",
      "organizations_url": "https://api.github.com/users/TokenHash/orgs",
      "repos_url": "https://api.github.com/users/TokenHash/repos",
      "events_url": "https://api.github.com/users/TokenHash/events{/privacy}",
      "received_events_url": "https://api.github.com/users/TokenHash/received_events",
      "type": "User",
      "site_admin": false
    }
  }